odoo9_addon_project_timeline-9.0.1.0.0-py2.7-nspkg.pth
odoo9_addon_project_timeline-9.0.1.0.0.dist-info/DESCRIPTION.rst
odoo9_addon_project_timeline-9.0.1.0.0.dist-info/METADATA
odoo9_addon_project_timeline-9.0.1.0.0.dist-info/RECORD
odoo9_addon_project_timeline-9.0.1.0.0.dist-info/WHEEL
odoo9_addon_project_timeline-9.0.1.0.0.dist-info/metadata.json
odoo9_addon_project_timeline-9.0.1.0.0.dist-info/namespace_packages.txt
odoo9_addon_project_timeline-9.0.1.0.0.dist-info/top_level.txt
odoo_addons/project_timeline/README.rst
odoo_addons/project_timeline/__init__.py
odoo_addons/project_timeline/__openerp__.py
odoo_addons/project_timeline/demo/project_task_demo.xml
odoo_addons/project_timeline/i18n/de.po
odoo_addons/project_timeline/i18n/es.po
odoo_addons/project_timeline/i18n/fr.po
odoo_addons/project_timeline/i18n/hr.po
odoo_addons/project_timeline/i18n/pt.po
odoo_addons/project_timeline/i18n/pt_BR.po
odoo_addons/project_timeline/i18n/sl.po
odoo_addons/project_timeline/models/__init__.py
odoo_addons/project_timeline/models/project_task.py
odoo_addons/project_timeline/static/description/icon.png
odoo_addons/project_timeline/static/description/icon.svg
odoo_addons/project_timeline/static/xml/project_timeline.xml
odoo_addons/project_timeline/views/project_task_view.xml
